nodepingpy/__init__.py
nodepingpy/_utils.py
nodepingpy/accounts.py
nodepingpy/checks.py
nodepingpy/contactgroups.py
nodepingpy/contacts.py
nodepingpy/diagnostics.py
nodepingpy/information.py
nodepingpy/maintenance.py
nodepingpy/notificationprofiles.py
nodepingpy/notifications.py
nodepingpy/results.py
nodepingpy/schedules.py
nodepingpy/nptypes/__init__.py
nodepingpy/nptypes/checktypes.py
nodepingpy/nptypes/contacttypes.py
nodepingpy/nptypes/diagtypes.py
nodepingpy/nptypes/maintenancetypes.py
nodepingpy/nptypes/notificationtypes.py
nodepingpy/nptypes/resulttypes.py
nodepingpy-1.1.0.dist-info/licenses/LICENSE
nodepingpy-1.1.0.dist-info/METADATA
nodepingpy-1.1.0.dist-info/WHEEL
nodepingpy-1.1.0.dist-info/top_level.txt
nodepingpy-1.1.0.dist-info/RECORD
