Metadata-Version: 2.4
Name: nodepingpy
Version: 1.1.0
Summary: Python package for querying the NodePing API
Home-page: https://github.com/NodePing/nodepingpy
Author: NodePing
Author-email: support@nodeping.com
Classifier: Programming Language :: Python :: 3
Classifier: License :: OSI Approved :: MIT License
Classifier: Operating System :: OS Independent
License-File: LICENSE
Dynamic: author
Dynamic: author-email
Dynamic: classifier
Dynamic: description
Dynamic: description-content-type
Dynamic: home-page
Dynamic: license-file
Dynamic: summary
